pollination/direct_sun_hours/__init__.py
pollination/direct_sun_hours/_direct_sunlight_calc.py
pollination/direct_sun_hours/_postprocess.py
pollination/direct_sun_hours/_prepare_folder.py
pollination/direct_sun_hours/entry.py
pollination_direct_sun_hours.viz-0.5.29.dist-info/LICENSE
pollination_direct_sun_hours.viz-0.5.29.dist-info/METADATA
pollination_direct_sun_hours.viz-0.5.29.dist-info/WHEEL
pollination_direct_sun_hours.viz-0.5.29.dist-info/top_level.txt
pollination_direct_sun_hours.viz-0.5.29.dist-info/RECORD
