Metadata-Version: 2.1
Name: pollination-direct-sun-hours.viz
Version: 0.5.29
Summary: Direct sun hours recipe for Pollination.
Home-page: https://github.com/pollination/direct-sun-hours
Author: ladybug-tools
Author-email: info@ladybug.tools
Maintainer: mostapha, ladybug-tools
Maintainer-email: mostapha@ladybug.tools, info@ladybug.tools
License: PolyForm Shield License 1.0.0, https://polyformproject.org/wp-content/uploads/2020/06/PolyForm-Shield-1.0.0.txt
Project-URL: icon, https://raw.githubusercontent.com/ladybug-tools/artwork/master/icons_components/honeybee/png/directsun.png
Project-URL: docker, https://hub.docker.com/r/ladybugtools/honeybee-radiance
Keywords: honeybee,radiance,ladybug-tools,daylight,direct-sun-hours
License-File: LICENSE
Requires-Dist: pollination-honeybee-radiance (>=0.22.46)
Requires-Dist: pollination-honeybee-radiance-postprocess (>=0.0.48)
Requires-Dist: pollination-ladybug (>=0.2.4)
Requires-Dist: pollination-alias (>=0.11.9)
Requires-Dist: pollination-path (>=0.3.2)
Provides-Extra: viz
Requires-Dist: pollination-honeybee-display (>=0.1.15) ; extra == 'viz'
